fdsreader/__init__.py
fdsreader/_version.py
fdsreader/settings.py
fdsreader/simulation.py
fdsreader/bndf/__init__.py
fdsreader/bndf/obstruction.py
fdsreader/bndf/obstruction_collection.py
fdsreader/bndf/utils.py
fdsreader/devc/__init__.py
fdsreader/devc/device.py
fdsreader/devc/device_collection.py
fdsreader/evac/__init__.py
fdsreader/evac/evac_collection.py
fdsreader/evac/evacuation.py
fdsreader/export/__init__.py
fdsreader/export/obst_exporter.py
fdsreader/export/sim_exporter.py
fdsreader/export/slcf_exporter.py
fdsreader/export/smoke3d_exporter.py
fdsreader/fds_classes/__init__.py
fdsreader/fds_classes/mesh.py
fdsreader/fds_classes/mesh_collection.py
fdsreader/fds_classes/surface.py
fdsreader/fds_classes/ventilation.py
fdsreader/geom/__init__.py
fdsreader/geom/geometry.py
fdsreader/geom/geometry_collection.py
fdsreader/isof/__init__.py
fdsreader/isof/isosurface.py
fdsreader/isof/isosurface_collection.py
fdsreader/part/__init__.py
fdsreader/part/particle.py
fdsreader/part/particle_collection.py
fdsreader/pl3d/__init__.py
fdsreader/pl3d/pl3d.py
fdsreader/pl3d/plot3D_collection.py
fdsreader/slcf/__init__.py
fdsreader/slcf/geomslice.py
fdsreader/slcf/geomslice_collection.py
fdsreader/slcf/slice.py
fdsreader/slcf/slice_collection.py
fdsreader/smoke3d/__init__.py
fdsreader/smoke3d/smoke3D_collection.py
fdsreader/smoke3d/smoke3d.py
fdsreader/utils/__init__.py
fdsreader/utils/data.py
fdsreader/utils/dimension.py
fdsreader/utils/extent.py
fdsreader/utils/fortran_data.py
fdsreader/utils/misc.py
fdsreader-1.11.7.dist-info/licenses/LICENSE
fdsreader-1.11.7.dist-info/METADATA
fdsreader-1.11.7.dist-info/WHEEL
fdsreader-1.11.7.dist-info/top_level.txt
fdsreader-1.11.7.dist-info/RECORD
