Metadata-Version: 2.4
Name: fdsreader
Version: 1.11.7
Summary: Python reader for data generated by FDS.
Author-email: "FZJ IAS-7 (Jan Vogelsang, Prof. Dr. Lukas Arnold, Tristan Hehnen)" <j.vogelsang@fz-juelich.de>
License:    GNU GENERAL PUBLIC LICENSE
Project-URL: Repository, https://github.com/FireDynamics/fdsreader
Classifier: Programming Language :: Python :: 3
Classifier: Operating System :: OS Independent
Classifier: License :: OSI Approved :: GNU Lesser General Public License v3 (LGPLv3)
Requires-Python: >=3.6
License-File: LICENSE
Requires-Dist: incremental
Requires-Dist: numpy
Requires-Dist: typing_extensions
Provides-Extra: dev
Requires-Dist: pytest>=6.0; extra == "dev"
Dynamic: license-file
